Metadata-Version: 2.1
Name: idun-guardian-client-beta-test
Version: 0.1b5
Summary: Python SDK for communication with the IDUN Guardian earbuds and IDUN cloud
Author-email: IDUN Technologies <contact@iduntechnologies.com>
Classifier: Development Status :: 1 - Planning
Classifier: License :: Other/Proprietary License
Classifier: Topic :: Software Development :: Libraries
Classifier: Operating System :: OS Independent
Classifier: Programming Language :: Python :: 3.10
Classifier: Natural Language :: English
Requires-Python: >=3.10
Requires-Dist: asyncio (~=3.4.3)
Requires-Dist: pycryptodome (~=3.15.0)
Requires-Dist: bleak (~=0.18.1)
Requires-Dist: python-dotenv (~=0.21.0)
Requires-Dist: websockets (~=10.3)
Requires-Dist: requests (~=2.28.1)
Requires-Dist: numpy (~=1.23.3)
Requires-Dist: pydantic (~=1.10.2)
